osemosys2iamc/__init__.py
osemosys2iamc/resultify.py
osemosys2iamc-0.2.2.dist-info/LICENSE.txt
osemosys2iamc-0.2.2.dist-info/METADATA
osemosys2iamc-0.2.2.dist-info/WHEEL
osemosys2iamc-0.2.2.dist-info/entry_points.txt
osemosys2iamc-0.2.2.dist-info/top_level.txt
osemosys2iamc-0.2.2.dist-info/RECORD
