Metadata-Version: 2.1
Name: osemosys2iamc
Version: 0.2.2
Summary: A utility package to convert OSeMOSYS results into IAMC format
Home-page: https://github.com/osemosys/osemosys2iamc/
Author: Will Usher
Author-email: wusher@kth.se
License: MIT
Project-URL: Source, https://github.com/osemosys/osemosys2iamc/
Project-URL: Tracker, https://github.com/osemosys/osemosys2iamc/issues
Platform: any
Classifier: Development Status :: 4 - Beta
Classifier: Programming Language :: Python
Requires-Python: >=3.8
License-File: LICENSE.txt
Requires-Dist: matplotlib
Requires-Dist: pandas
Requires-Dist: pyam-iamc >=1.0
Requires-Dist: iso3166
Requires-Dist: importlib-metadata ; python_version < "3.8"
Provides-Extra: testing
Requires-Dist: setuptools ; extra == 'testing'
Requires-Dist: pytest ; extra == 'testing'
Requires-Dist: pytest-cov ; extra == 'testing'
